paji_sdk/__init__.py
paji_sdk/__init__.pyi
paji_sdk/base/__init__.py
paji_sdk/base/__init__.pyi
paji_sdk/base/base_types.py
paji_sdk/base/base_types.pyi
paji_sdk/base/exceptions.py
paji_sdk/base/exceptions.pyi
paji_sdk-0.2.2.dist-info/METADATA
paji_sdk-0.2.2.dist-info/WHEEL
paji_sdk-0.2.2.dist-info/top_level.txt
paji_sdk-0.2.2.dist-info/RECORD
