Metadata-Version: 2.1
Name: paji-sdk
Version: 0.2.2
Summary: Python 開發工具包
Home-page: https://github.com/marco79423/paji-sdk.py
Author: 兩大類
Author-email: marco79423@gmail.com
License: UNKNOWN
Platform: UNKNOWN
Classifier: Programming Language :: Python :: 3.6
Classifier: Programming Language :: Python :: 3.7
Classifier: Programming Language :: Python :: 3.8
Classifier: Programming Language :: Python :: 3.9
Requires-Python: >=3.6
